rtl/top.v
// rtl/top.v
`timescale 1ns/1ps
module top (
    input  wire         clk,
    input  wire         rst_n,
    input  wire         in_valid,
    input  wire [31:0]  in_data,
    output reg          out_valid,
    output reg  [31:0]  out_data
);

  reg [31:0] sum;
  reg in_valid_d;       // pipeline register to reflect 1-cycle latency
  reg [31:0] in_data_d;

  always @(posedge clk or negedge rst_n) begin
    if (!rst_n) begin
      sum <= 32'h0;
      in_valid_d <= 1'b0;
      in_data_d <= 32'h0;
      out_valid <= 1'b0;
      out_data <= 32'h0;
    end else begin
      // sample and pipeline input
      in_valid_d <= in_valid;
      in_data_d <= in_data;

      if (in_valid) begin
        sum <= sum + in_data; // wrap-around modulo 2^32 (Verilog default)
      end

      // output one-cycle-later behavior
      out_valid <= in_valid_d;
      if (in_valid_d) begin
        out_data <= sum; // note: sum was updated in same cycle as sampled input; pipeline chosen so golden must match
      end else begin
        out_data <= 32'h0;
      end
    end
  end

endmodule

results/wave.vcd
$version Generated by VerilatedVcd $end
$timescale 1ps $end
 $scope module TOP $end
  $var wire 1 & clk $end
  $var wire 1 ' rst_n $end
  $var wire 1 ( in_valid $end
  $var wire 32 ) in_data [31:0] $end
  $var wire 1 * out_valid $end
  $var wire 32 + out_data [31:0] $end
  $scope module top $end
   $var wire 1 & clk $end
   $var wire 1 ' rst_n $end
   $var wire 1 ( in_valid $end
   $var wire 32 ) in_data [31:0] $end
   $var wire 1 * out_valid $end
   $var wire 32 + out_data [31:0] $end
   $var wire 32 # sum [31:0] $end
   $var wire 1 $ in_valid_d $end
   $var wire 32 % in_data_d [31:0] $end
  $upscope $end
 $upscope $end
$enddefinitions $end


#0
b00000000000000000000000000000000 #
0$
b00000000000000000000000000000000 %
1&
0'
0(
b00000000000000000000000000000000 )
0*
b00000000000000000000000000000000 +
#1
0&
#2
1&
#3
0&
#4
b11000000001100011010101100011100 #
1$
b00011100100000000011000101111111 %
1'
#5
0$
b00000000000000000000000000000000 %
1&
1*
b11000000001100011010101100011100 +
#6
b11000110100110001100010111101101 #
1$
b00000110011001110001101011010001 %
0&
0*
b00000000000000000000000000000000 +
#7
0$
b00000000000000000000000000000000 %
1&
1*
b11000110100110001100010111101101 +
#8
b10000100011011110000011011101000 #
1$
b10111101110101100100000011111011 %
0&
0*
b00000000000000000000000000000000 +
#9
0$
b00000000000000000000000000000000 %
1&
1*
b10000100011011110000011011101000 +
#10
b11001010110101110101100100111111 #
1$
b01000110011010000101001001010111 %
0&
0*
b00000000000000000000000000000000 +
#11
0$
b00000000000000000000000000000000 %
1&
1*
b11001010110101110101100100111111 +
#12
b00001001100010001001010011001111 #
1$
b00111110101100010011101110010000 %
0&
0*
b00000000000000000000000000000000 +
#13
0$
b00000000000000000000000000000000 %
1&
1*
b00001001100010001001010011001111 +
#14
b01000010101011001110101110101101 #
1$
b00111001001001000101011011011110 %
0&
0*
b00000000000000000000000000000000 +
#15
0$
b00000000000000000000000000000000 %
1&
1*
b01000010101011001110101110101101 +
#16
b01100110011001011010110110010110 #
1$
b00100011101110001100000111101001 %
0&
0*
b00000000000000000000000000000000 +
#17
0$
b00000000000000000000000000000000 %
1&
1*
b01100110011001011010110110010110 +
#18
b00100010111011110000111000111111 #
1$
b10111100100010010110000010101001 %
0&
0*
b00000000000000000000000000000000 +
#19
0$
b00000000000000000000000000000000 %
1&
1*
b00100010111011110000111000111111 +
#20
b00111101001011000010110111100110 #
1$
b00011010001111010001111110100111 %
0&
0*
b00000000000000000000000000000000 +
#21
0$
b00000000000000000000000000000000 %
1&
1*
b00111101001011000010110111100110 +
#22
b11101010011010000101101101010011 #
1$
b10101101001111000010110101101101 %
0&
0*
b00000000000000000000000000000000 +
#23
0$
b00000000000000000000000000000000 %
1&
1*
b11101010011010000101101101010011 +
#24
b10101000000001001100001000000110 #
1$
b10111101100111000110011010110011 %
0&
0*
b00000000000000000000000000000000 +
#25
0$
b00000000000000000000000000000000 %
1&
1*
b10101000000001001100001000000110 +
#26
b10001100011010101010001101010110 #
1$
b11100100011001011110000101010000 %
0&
0*
b00000000000000000000000000000000 +
#27
0$
b00000000000000000000000000000000 %
1&
1*
b10001100011010101010001101010110 +
#28
b00011000000001111100011110001010 #
1$
b10001011100111010010010000110100 %
0&
0*
b00000000000000000000000000000000 +
#29
0$
b00000000000000000000000000000000 %
1&
1*
b00011000000001111100011110001010 +
#30
b00101110010010010110011100001100 #
1$
b00010110010000011001111110000010 %
0&
0*
b00000000000000000000000000000000 +
#31
0$
b00000000000000000000000000000000 %
1&
1*
b00101110010010010110011100001100 +
#32
b11000101011100111110101101110101 #
1$
b10010111001010101000010001101001 %
0&
0*
b00000000000000000000000000000000 +
#33
0$
b00000000000000000000000000000000 %
1&
1*
b11000101011100111110101101110101 +
#34
b00110001011101101111110100001110 #
1$
b01101100000000110001000110011001 %
0&
0*
b00000000000000000000000000000000 +
#35
0$
b00000000000000000000000000000000 %
1&
1*
b00110001011101101111110100001110 +
#36
b00111001100110011110011000000001 #
1$
b00001000001000101110100011110011 %
0&
0*
b00000000000000000000000000000000 +
#37
0$
b00000000000000000000000000000000 %
1&
1*
b00111001100110011110011000000001 +
#38
b01000001001110101011000001101111 #
1$
b00000111101000001100101001101110 %
0&
0*
b00000000000000000000000000000000 +
#39
0$
b00000000000000000000000000000000 %
1&
1*
b01000001001110101011000001101111 +
#40
b01011001001101110001100111001001 #
1$
b00010111111111000110100101011010 %
0&
0*
b00000000000000000000000000000000 +
#41
0$
b00000000000000000000000000000000 %
1&
1*
b01011001001101110001100111001001 +
#42
b10010001001011111100001001010100 #
1$
b00110111111110001010100010001011 %
0&
0*
b00000000000000000000000000000000 +
#43
0$
b00000000000000000000000000000000 %
1&
1*
b10010001001011111100001001010100 +
#44
b11001100101111110110110001101100 #
1$
b00111011100011111010101000011000 %
0&
0*
b00000000000000000000000000000000 +
#45
0$
b00000000000000000000000000000000 %
1&
1*
b11001100101111110110110001101100 +
#46
b01001110000111100110001100111101 #
1$
b10000001010111101111011011010001 %
0&
0*
b00000000000000000000000000000000 +
#47
0$
b00000000000000000000000000000000 %
1&
1*
b01001110000111100110001100111101 +
#48
b11101000001111000100100110000001 #
1$
b10011010000111011110011001000100 %
0&
0*
b00000000000000000000000000000000 +
#49
0$
b00000000000000000000000000000000 %
1&
1*
b11101000001111000100100110000001 +
#50
b11101111000001110101100100110100 #
1$
b00000110110010110000111110110011 %
0&
0*
b00000000000000000000000000000000 +
#51
0$
b00000000000000000000000000000000 %
1&
1*
b11101111000001110101100100110100 +
#52
b01111110101101010001101011011010 #
1$
b10001111101011011100000110100110 %
0&
0*
b00000000000000000000000000000000 +
#53
0$
b00000000000000000000000000000000 %
1&
1*
b01111110101101010001101011011010 +
#54
b10110001100111000010000100000011 #
1$
b00110010111001110000011000101001 %
0&
0*
b00000000000000000000000000000000 +
#55
0$
b00000000000000000000000000000000 %
1&
1*
b10110001100111000010000100000011 +
#56
b01101000111010010011000010110100 #
1$
b10110111010011010000111110110001 %
0&
0*
b00000000000000000000000000000000 +
#57
0$
b00000000000000000000000000000000 %
1&
1*
b01101000111010010011000010110100 +
#58
b00001111010010000000010000111101 #
1$
b10100110010111101101001110001001 %
0&
0*
b00000000000000000000000000000000 +
#59
0$
b00000000000000000000000000000000 %
1&
1*
b00001111010010000000010000111101 +
#60
b11000010110100100000110011001001 #
1$
b10110011100010100000100010001100 %
0&
0*
b00000000000000000000000000000000 +
#61
0$
b00000000000000000000000000000000 %
1&
1*
b11000010110100100000110011001001 +
#62
b01001110010100110101010110111111 #
1$
b10001011100000010100100011110110 %
0&
0*
b00000000000000000000000000000000 +
#63
0$
b00000000000000000000000000000000 %
1&
1*
b01001110010100110101010110111111 +
#64
b10111001101110001111110001100011 #
1$
b01101011011001011010011010100100 %
0&
0*
b00000000000000000000000000000000 +
#65
0$
b00000000000000000000000000000000 %
1&
1*
b10111001101110001111110001100011 +
#66
b11110010001001111100100001000011 #
1$
b00111000011011101100101111100000 %
0&
0*
b00000000000000000000000000000000 +
#67
0$
b00000000000000000000000000000000 %
1&
1*
b11110010001001111100100001000011 +
#68
b01100101001001110010010101101101 #
1$
b01110010111111110101110100101010 %
0&
0*
b00000000000000000000000000000000 +
#69
0$
b00000000000000000000000000000000 %
1&
1*
b01100101001001110010010101101101 +
#70
b11111100000000010100001100011001 #
1$
b10010110110110100001110110101100 %
0&
0*
b00000000000000000000000000000000 +
#71
0$
b00000000000000000000000000000000 %
1&
1*
b11111100000000010100001100011001 +
#72
b01000011001110001100010010101001 #
1$
b01000111001101111000000110010000 %
0&
0*
b00000000000000000000000000000000 +
#73
0$
b00000000000000000000000000000000 %
1&
1*
b01000011001110001100010010101001 +
#74
b00010010011011111001101000110100 #
1$
b11001111001101101101010110001011 %
0&
0*
b00000000000000000000000000000000 +
#75
0$
b00000000000000000000000000000000 %
1&
1*
b00010010011011111001101000110100 +
#76
b11110000111110100001000101111111 #
1$
b11011110100010100111011101001011 %
0&
0*
b00000000000000000000000000000000 +
#77
0$
b00000000000000000000000000000000 %
1&
1*
b11110000111110100001000101111111 +
#78
b11110010101000111111100010011110 #
1$
b00000001101010011110011100011111 %
0&
0*
b00000000000000000000000000000000 +
#79
0$
b00000000000000000000000000000000 %
1&
1*
b11110010101000111111100010011110 +
#80
b10110100111001010010101110101001 #
1$
b11000010010000010011001100001011 %
0&
0*
b00000000000000000000000000000000 +
#81
0$
b00000000000000000000000000000000 %
1&
1*
b10110100111001010010101110101001 +
#82
b10000011001011110101011101100110 #
1$
b11001110010010100010101110111101 %
0&
0*
b00000000000000000000000000000000 +
#83
0$
b00000000000000000000000000000000 %
1&
1*
b10000011001011110101011101100110 +
#84
b10101100000011101100011000101010 #
1$
b00101000110111110110111011000100 %
0&
0*
b00000000000000000000000000000000 +
#85
0$
b00000000000000000000000000000000 %
1&
1*
b10101100000011101100011000101010 +
#86
b01011110110010000000100110100100 #
1$
b10110010101110010100001101111010 %
0&
0*
b00000000000000000000000000000000 +
#87
0$
b00000000000000000000000000000000 %
1&
1*
b01011110110010000000100110100100 +
#88
b11001010111110000111111010110101 #
1$
b01101100001100000111010100010001 %
0&
0*
b00000000000000000000000000000000 +
#89
0$
b00000000000000000000000000000000 %
1&
1*
b11001010111110000111111010110101 +
#90
b00100010000100110010011100101011 #
1$
b01010111000110101010100001110110 %
0&
0*
b00000000000000000000000000000000 +
#91
0$
b00000000000000000000000000000000 %
1&
1*
b00100010000100110010011100101011 +
#92
b01101001001101011011101010110100 #
1$
b01000111001000101001001110001001 %
0&
0*
b00000000000000000000000000000000 +
#93
0$
b00000000000000000000000000000000 %
1&
1*
b01101001001101011011101010110100 +
#94
b10010001000000110011101111100100 #
1$
b00100111110011011000000100110000 %
0&
0*
b00000000000000000000000000000000 +
#95
0$
b00000000000000000000000000000000 %
1&
1*
b10010001000000110011101111100100 +
#96
b11001000001000100000100101011111 #
1$
b00110111000111101100110101111011 %
0&
0*
b00000000000000000000000000000000 +
#97
0$
b00000000000000000000000000000000 %
1&
1*
b11001000001000100000100101011111 +
#98
b10111101001011011111001111000010 #
1$
b11110101000010111110101001100011 %
0&
0*
b00000000000000000000000000000000 +
#99
0$
b00000000000000000000000000000000 %
1&
1*
b10111101001011011111001111000010 +
#100
b10000000101000100100110110110000 #
1$
b11000011011101000101100111101110 %
0&
0*
b00000000000000000000000000000000 +
#101
0$
b00000000000000000000000000000000 %
1&
1*
b10000000101000100100110110110000 +
#102
b11010110110011010101110100101001 #
1$
b01010110001010110000111101111001 %
0&
0*
b00000000000000000000000000000000 +
#103
0$
b00000000000000000000000000000000 %
1&
1*
b11010110110011010101110100101001 +
#104
b11110000111101111101000100010110 #
1$
b00011010001010100111001111101101 %
0&
0*
b00000000000000000000000000000000 +
#105
0$
b00000000000000000000000000000000 %
1&
1*
b11110000111101111101000100010110 +
#106
b00001000101101100000001000100111 #
1$
b00010111101111100011000100010001 %
0&
0*
b00000000000000000000000000000000 +
#107
0$
b00000000000000000000000000000000 %
1&
1*
b00001000101101100000001000100111 +
#108
b01101001111110001110110010100100 #
1$
b01100001010000101110101001111101 %
0&
0*
b00000000000000000000000000000000 +
#109
0$
b00000000000000000000000000000000 %
1&
1*
b01101001111110001110110010100100 +
#110
b10000010101110110101010000111011 #
1$
b00011000110000100110011110010111 %
0&
0*
b00000000000000000000000000000000 +
#111
0$
b00000000000000000000000000000000 %
1&
1*
b10000010101110110101010000111011 +
#112
b11011110101000010110011011001001 #
1$
b01011011111001100001001010001110 %
0&
0*
b00000000000000000000000000000000 +
#113
0$
b00000000000000000000000000000000 %
1&
1*
b11011110101000010110011011001001 +
#114
b10110111100101101100101011011100 #
1$
b11011000111101010110010000010011 %
0&
0*
b00000000000000000000000000000000 +
#115
0$
b00000000000000000000000000000000 %
1&
1*
b10110111100101101100101011011100 +
#116
b00001111101001000100011001001101 #
1$
b01011000000011010111101101110001 %
0&
0*
b00000000000000000000000000000000 +
#117
0$
b00000000000000000000000000000000 %
1&
1*
b00001111101001000100011001001101 +
#118
b10101010001100100001000001010000 #
1$
b10011010100011011100101000000011 %
0&
0*
b00000000000000000000000000000000 +
#119
0$
b00000000000000000000000000000000 %
1&
1*
b10101010001100100001000001010000 +
#120
b11101101111010011011001111110110 #
1$
b01000011101101111010001110100110 %
0&
0*
b00000000000000000000000000000000 +
#121
0$
b00000000000000000000000000000000 %
1&
1*
b11101101111010011011001111110110 +
#122
b10111100100010011010100101110101 #
1$
b11001110100111111111010101111111 %
0&
0*
b00000000000000000000000000000000 +
#123
0$
b00000000000000000000000000000000 %
1&
1*
b10111100100010011010100101110101 +
#124
b11000111101010010011101011011000 #
1$
b00001011000111111001000101100011 %
0&
0*
b00000000000000000000000000000000 +
#125
0$
b00000000000000000000000000000000 %
1&
1*
b11000111101010010011101011011000 +
#126
b10000010011110001110111010101000 #
1$
b10111010110011111011001111010000 %
0&
0*
b00000000000000000000000000000000 +
#127
0$
b00000000000000000000000000000000 %
1&
1*
b10000010011110001110111010101000 +
#128
b11111000000101011100110100001110 #
1$
b01110101100111001101111001100110 %
0&
0*
b00000000000000000000000000000000 +
#129
0$
b00000000000000000000000000000000 %
1&
1*
b11111000000101011100110100001110 +
#130
b10000001010111000000101110010011 #
1$
b10001001010001100011111010000101 %
0&
0*
b00000000000000000000000000000000 +
#131
0$
b00000000000000000000000000000000 %
1&
1*
b10000001010111000000101110010011 +
#132
b10100001010100001010011100001011 #
1$
b00011111111101001001101101111000 %
0&
0*
b00000000000000000000000000000000 +
#133
0$
b00000000000000000000000000000000 %
1&
1*
b10100001010100001010011100001011 +
#134
b10011010011011101100010001010111 #
1$
b11111001000111100001110101001100 %
0&
0*
b00000000000000000000000000000000 +
#135
0$
b00000000000000000000000000000000 %
1&
1*
b10011010011011101100010001010111 +
#136
b10000110100010100101000011111000 #
1$
b11101100000110111000110010100001 %
0&
0*
b00000000000000000000000000000000 +
#137
0$
b00000000000000000000000000000000 %
1&
1*
b10000110100010100101000011111000 +
#138
b11100111011100011111001000001011 #
1$
b01100000111001111010000100010011 %
0&
0*
b00000000000000000000000000000000 +
#139
0$
b00000000000000000000000000000000 %
1&
1*
b11100111011100011111001000001011 +
#140
b11111011100111100011000111110011 #
1$
b00010100001011000011111111101000 %
0&
0*
b00000000000000000000000000000000 +
#141
0$
b00000000000000000000000000000000 %
1&
1*
b11111011100111100011000111110011 +
#142
b10001000111100001011101011100100 #
1$
b10001101010100101000100011110001 %
0&
0*
b00000000000000000000000000000000 +
#143
0$
b00000000000000000000000000000000 %
1&
1*
b10001000111100001011101011100100 +
#144
b11010011111111100111011000100101 #
1$
b01001011000011011011101101000001 %
0&
0*
b00000000000000000000000000000000 +
#145
0$
b00000000000000000000000000000000 %
1&
1*
b11010011111111100111011000100101 +
#146
b10101000010100100101001101010111 #
1$
b11010100010100111101110100110010 %
0&
0*
b00000000000000000000000000000000 +
#147
0$
b00000000000000000000000000000000 %
1&
1*
b10101000010100100101001101010111 +
#148
b01001001010000001101110100000101 #
1$
b10100000111011101000100110101110 %
0&
0*
b00000000000000000000000000000000 +
#149
0$
b00000000000000000000000000000000 %
1&
1*
b01001001010000001101110100000101 +
#150
b11100111100110000010110001111111 #
1$
b10011110010101110100111101111010 %
0&
0*
b00000000000000000000000000000000 +
#151
0$
b00000000000000000000000000000000 %
1&
1*
b11100111100110000010110001111111 +
#152
b11001010010001010010001110101110 #
1$
b11100010101011001111011100101111 %
0&
0*
b00000000000000000000000000000000 +
#153
0$
b00000000000000000000000000000000 %
1&
1*
b11001010010001010010001110101110 +
#154
b10100110110111011111011001101111 #
1$
b11011100100110001101001011000001 %
0&
0*
b00000000000000000000000000000000 +
#155
0$
b00000000000000000000000000000000 %
1&
1*
b10100110110111011111011001101111 +
#156
b00000011011100100001001101011111 #
1$
b01011100100101000001110011110000 %
0&
0*
b00000000000000000000000000000000 +
#157
0$
b00000000000000000000000000000000 %
1&
1*
b00000011011100100001001101011111 +
#158
b10010111001111110110110100011110 #
1$
b10010011110011010101100110111111 %
0&
0*
b00000000000000000000000000000000 +
#159
0$
b00000000000000000000000000000000 %
1&
1*
b10010111001111110110110100011110 +
#160
b11001000011110010100000001001010 #
1$
b00110001001110011101001100101100 %
0&
0*
b00000000000000000000000000000000 +
#161
0$
b00000000000000000000000000000000 %
1&
1*
b11001000011110010100000001001010 +
#162
b01111100110110000001001000111010 #
1$
b10110100010111101101000111110000 %
0&
0*
b00000000000000000000000000000000 +
#163
0$
b00000000000000000000000000000000 %
1&
1*
b01111100110110000001001000111010 +
#164
b10001110101001100111000000001100 #
1$
b00010001110011100101110111010010 %
0&
0*
b00000000000000000000000000000000 +
#165
0$
b00000000000000000000000000000000 %
1&
1*
b10001110101001100111000000001100 +
#166
b10011010011000011001010110100101 #
1$
b00001011101110110010010110011001 %
0&
0*
b00000000000000000000000000000000 +
#167
0$
b00000000000000000000000000000000 %
1&
1*
b10011010011000011001010110100101 +
#168
b01000011101010100010001100111110 #
1$
b10101001010010001000110110011001 %
0&
0*
b00000000000000000000000000000000 +
#169
0$
b00000000000000000000000000000000 %
1&
1*
b01000011101010100010001100111110 +
#170
b01111110000000011010110111001100 #
1$
b00111010010101111000101010001110 %
0&
0*
b00000000000000000000000000000000 +
#171
0$
b00000000000000000000000000000000 %
1&
1*
b01111110000000011010110111001100 +
#172
b01000011111010010111110001010110 #
1$
b11000101111001111100111010001010 %
0&
0*
b00000000000000000000000000000000 +
#173
0$
b00000000000000000000000000000000 %
1&
1*
b01000011111010010111110001010110 +
#174
b10001101111111101101000010100011 #
1$
b01001010000101010101010001001101 %
0&
0*
b00000000000000000000000000000000 +
#175
0$
b00000000000000000000000000000000 %
1&
1*
b10001101111111101101000010100011 +
#176
b10001010001101100100101011101111 #
1$
b11111100001101110111101001001100 %
0&
0*
b00000000000000000000000000000000 +
#177
0$
b00000000000000000000000000000000 %
1&
1*
b10001010001101100100101011101111 +
#178
b10011110101000111000101000100000 #
1$
b00010100011011010011111100110001 %
0&
0*
b00000000000000000000000000000000 +
#179
0$
b00000000000000000000000000000000 %
1&
1*
b10011110101000111000101000100000 +
#180
b01111001100110011010010001000110 #
1$
b11011010111101100001101000100110 %
0&
0*
b00000000000000000000000000000000 +
#181
0$
b00000000000000000000000000000000 %
1&
1*
b01111001100110011010010001000110 +
#182
b10110101001100011101001100111110 #
1$
b00111011100110000010111011111000 %
0&
0*
b00000000000000000000000000000000 +
#183
0$
b00000000000000000000000000000000 %
1&
1*
b10110101001100011101001100111110 +
#184
b10010011000000111011001011110000 #
1$
b11011101110100011101111110110010 %
0&
0*
b00000000000000000000000000000000 +
#185
0$
b00000000000000000000000000000000 %
1&
1*
b10010011000000111011001011110000 +
#186
b10101100110111101110110111000000 #
1$
b00011001110110110011101011010000 %
0&
0*
b00000000000000000000000000000000 +
#187
0$
b00000000000000000000000000000000 %
1&
1*
b10101100110111101110110111000000 +
#188
b00001110001011101110000110010111 #
1$
b01100001010011111111001111010111 %
0&
0*
b00000000000000000000000000000000 +
#189
0$
b00000000000000000000000000000000 %
1&
1*
b00001110001011101110000110010111 +
#190
b01010101010110000010100011010000 #
1$
b01000111001010010100011100111001 %
0&
0*
b00000000000000000000000000000000 +
#191
0$
b00000000000000000000000000000000 %
1&
1*
b01010101010110000010100011010000 +
#192
b11001001011010101101101101100011 #
1$
b01110100000100101011001010010011 %
0&
0*
b00000000000000000000000000000000 +
#193
0$
b00000000000000000000000000000000 %
1&
1*
b11001001011010101101101101100011 +
#194
b01101100001001110001001010010010 #
1$
b10100010101111000011011100101111 %
0&
0*
b00000000000000000000000000000000 +
#195
0$
b00000000000000000000000000000000 %
1&
1*
b01101100001001110001001010010010 +
#196
b01000001101011110101010101110000 #
1$
b11010101100010000100001011011110 %
0&
0*
b00000000000000000000000000000000 +
#197
0$
b00000000000000000000000000000000 %
1&
1*
b01000001101011110101010101110000 +
#198
b10011111000101001111100110110001 #
1$
b01011101011001011010010001000001 %
0&
0*
b00000000000000000000000000000000 +
#199
0$
b00000000000000000000000000000000 %
1&
1*
b10011111000101001111100110110001 +
#200
b11001000101110001010110010011010 #
1$
b00101001101000111011001011101001 %
0&
0*
b00000000000000000000000000000000 +
#201
0$
b00000000000000000000000000000000 %
1&
1*
b11001000101110001010110010011010 +
#202
b00100111011111001101101010100010 #
1$
b01011110110001000010111000001000 %
0&
0*
b00000000000000000000000000000000 +
#203
0$
b00000000000000000000000000000000 %
1&
1*
b00100111011111001101101010100010 +
#204
b10000010011011111101111111110101 #
1$
b01011010111100110000010101010011 %
0&
0*
b00000000000000000000000000000000 +
#205
0$
b00000000000000000000000000000000 %
1&
1*
b10000010011011111101111111110101 +
#206
b10111000000100100010000010100011 #
1$
b00110101101000100100000010101110 %
0&
0*
b00000000000000000000000000000000 +
#207
0$
b00000000000000000000000000000000 %
1&
1*
b10111000000100100010000010100011 +
#208
b01100011101000101011101001000111 #
1$
b10101011100100001001100110100100 %
0&
0*
b00000000000000000000000000000000 +
#209
0$
b00000000000000000000000000000000 %
1&
1*
b01100011101000101011101001000111 +
#210
b10100111111110110110001011001100 #
1$
b01000100010110001010100010000101 %
0&
0*
b00000000000000000000000000000000 +
#211
0$
b00000000000000000000000000000000 %
1&
1*
b10100111111110110110001011001100 +
#212
b01011011101001011110000111001010 #
1$
b10110011101010100111111011111110 %
0&
0*
b00000000000000000000000000000000 +
#213
0$
b00000000000000000000000000000000 %
1&
1*
b01011011101001011110000111001010 +
#214
b01001011011011100111101000010011 #
1$
b11101111110010001001100001001001 %
0&
0*
b00000000000000000000000000000000 +
#215
0$
b00000000000000000000000000000000 %
1&
1*
b01001011011011100111101000010011 +
#216
b11111010011010110111010011101011 #
1$
b10101110111111001111101011011000 %
0&
0*
b00000000000000000000000000000000 +
#217
0$
b00000000000000000000000000000000 %
1&
1*
b11111010011010110111010011101011 +
#218
b10100000010100010001101010010110 #
1$
b10100101111001011010010110101011 %
0&
0*
b00000000000000000000000000000000 +
#219
0$
b00000000000000000000000000000000 %
1&
1*
b10100000010100010001101010010110 +
#220
b10110010100110001000100111101101 #
1$
b00010010010001110110111101010111 %
0&
0*
b00000000000000000000000000000000 +
#221
0$
b00000000000000000000000000000000 %
1&
1*
b10110010100110001000100111101101 +
#222
b01001110100010001000110001100000 #
1$
b10011011111100000000001001110011 %
0&
0*
b00000000000000000000000000000000 +
#223
0$
b00000000000000000000000000000000 %
1&
1*
b01001110100010001000110001100000 +
#224
b11110001000101100111110001000011 #
1$
b10100010100011011110111111100011 %
0&
0*
b00000000000000000000000000000000 +
#225
0$
b00000000000000000000000000000000 %
1&
1*
b11110001000101100111110001000011 +
#226
b00011100111001100011101001000100 #
1$
b00101011110011111011111000000001 %
0&
0*
b00000000000000000000000000000000 +
#227
0$
b00000000000000000000000000000000 %
1&
1*
b00011100111001100011101001000100 +
#228
b10100101101000111001111001001011 #
1$
b10001000101111010110010000000111 %
0&
0*
b00000000000000000000000000000000 +
#229
0$
b00000000000000000000000000000000 %
1&
1*
b10100101101000111001111001001011 +
#230
b01100000010010111010110000011111 #
1$
b10111010101010000000110111010100 %
0&
0*
b00000000000000000000000000000000 +
#231
0$
b00000000000000000000000000000000 %
1&
1*
b01100000010010111010110000011111 +
#232
b10011110111101111001100111101010 #
1$
b00111110101010111110110111001011 %
0&
0*
b00000000000000000000000000000000 +
#233
0$
b00000000000000000000000000000000 %
1&
1*
b10011110111101111001100111101010 +
#234
b11001000110011000101100011011001 #
1$
b00101001110101001011111011101111 %
0&
0*
b00000000000000000000000000000000 +
#235
0$
b00000000000000000000000000000000 %
1&
1*
b11001000110011000101100011011001 +
#236
b00111111001000110000100001001011 #
1$
b01110110010101101010111101110010 %
0&
0*
b00000000000000000000000000000000 +
#237
0$
b00000000000000000000000000000000 %
1&
1*
b00111111001000110000100001001011 +
#238
b10100000010001110000011001000010 #
1$
b01100001001000111111110111110111 %
0&
0*
b00000000000000000000000000000000 +
#239
0$
b00000000000000000000000000000000 %
1&
1*
b10100000010001110000011001000010 +
#240
b11100101011000100101001100110101 #
1$
b01000101000110110100110011110011 %
0&
0*
b00000000000000000000000000000000 +
#241
0$
b00000000000000000000000000000000 %
1&
1*
b11100101011000100101001100110101 +
#242
b11100010101100111011101000011011 #
1$
b11111101010100010110011011100110 %
0&
0*
b00000000000000000000000000000000 +
#243
0$
b00000000000000000000000000000000 %
1&
1*
b11100010101100111011101000011011 +
#244
b11001111100110100010100110111101 #
1$
b11101100111001100110111110100010 %
0&
0*
b00000000000000000000000000000000 +
#245
0$
b00000000000000000000000000000000 %
1&
1*
b11001111100110100010100110111101 +
#246
b01110011011100010010111111100101 #
1$
b10100011110101110000011000101000 %
0&
0*
b00000000000000000000000000000000 +
#247
0$
b00000000000000000000000000000000 %
1&
1*
b01110011011100010010111111100101 +
#248
b00100011100111001001000110101001 #
1$
b10110000001010110110000111000100 %
0&
0*
b00000000000000000000000000000000 +
#249
0$
b00000000000000000000000000000000 %
1&
1*
b00100011100111001001000110101001 +
#250
b10110010001100001101001111100010 #
1$
b10001110100101000100001000111001 %
0&
0*
b00000000000000000000000000000000 +
#251
0$
b00000000000000000000000000000000 %
1&
1*
b10110010001100001101001111100010 +
#252
b11101010011010011000011100001000 #
1$
b00111000001110001011001100100110 %
0&
0*
b00000000000000000000000000000000 +
#253
0$
b00000000000000000000000000000000 %
1&
1*
b11101010011010011000011100001000 +
#254
b10011001101011000110100000110111 #
1$
b10101111010000101110000100101111 %
0&
0*
b00000000000000000000000000000000 +
#255
0$
b00000000000000000000000000000000 %
1&
1*
b10011001101011000110100000110111 +
#256
b11101100101100001001100110110110 #
1$
b01010011000001000011000101111111 %
0&
0*
b00000000000000000000000000000000 +
#257
0$
b00000000000000000000000000000000 %
1&
1*
b11101100101100001001100110110110 +
#258
b11000100011101011011111001011011 #
1$
b11010111110001010010010010100101 %
0&
0*
b00000000000000000000000000000000 +
#259
0$
b00000000000000000000000000000000 %
1&
1*
b11000100011101011011111001011011 +
#260
b10001001001001011111000100100111 #
1$
b11000100101100000011001011001100 %
0&
0*
b00000000000000000000000000000000 +
#261
0$
b00000000000000000000000000000000 %
1&
1*
b10001001001001011111000100100111 +
#262
b01001111110011011101111101100000 #
1$
b11000110101001111110111000111001 %
0&
0*
b00000000000000000000000000000000 +
#263
0$
b00000000000000000000000000000000 %
1&
1*
b01001111110011011101111101100000 +
#264
b01011110000111111101001001101101 #
1$
b00001110010100011111001100001101 %
0&
0*
b00000000000000000000000000000000 +
#265
0$
b00000000000000000000000000000000 %
1&
1*
b01011110000111111101001001101101 +
#266
b10011000110000101011011101100110 #
1$
b00111010101000101110010011111001 %
0&
0*
b00000000000000000000000000000000 +
#267
0$
b00000000000000000000000000000000 %
1&
1*
b10011000110000101011011101100110 +
#268
b01101011001001000101111100010001 #
1$
b11010010011000011010011110101011 %
0&
0*
b00000000000000000000000000000000 +
#269
0$
b00000000000000000000000000000000 %
1&
1*
b01101011001001000101111100010001 +
#270
b01110011010111000001011110110100 #
1$
b00001000001101111011100010100011 %
0&
0*
b00000000000000000000000000000000 +
#271
0$
b00000000000000000000000000000000 %
1&
1*
b01110011010111000001011110110100 +
#272
b01000001011100111001001100000010 #
1$
b11001110000101110111101101001110 %
0&
0*
b00000000000000000000000000000000 +
#273
0$
b00000000000000000000000000000000 %
1&
1*
b01000001011100111001001100000010 +
#274
b10010010001101010001101011111110 #
1$
b01010000110000011000011111111100 %
0&
0*
b00000000000000000000000000000000 +
#275
0$
b00000000000000000000000000000000 %
1&
1*
b10010010001101010001101011111110 +
#276
b11111000111001111101011101011001 #
1$
b01100110101100101011110001011011 %
0&
0*
b00000000000000000000000000000000 +
#277
0$
b00000000000000000000000000000000 %
1&
1*
b11111000111001111101011101011001 +
#278
b00111101011100101000000111110111 #
1$
b01000100100010101010101010011110 %
0&
0*
b00000000000000000000000000000000 +
#279
0$
b00000000000000000000000000000000 %
1&
1*
b00111101011100101000000111110111 +
#280
b01001110011001000011111001111000 #
1$
b00010000111100011011110010000001 %
0&
0*
b00000000000000000000000000000000 +
#281
0$
b00000000000000000000000000000000 %
1&
1*
b01001110011001000011111001111000 +
#282
b10000100011001110011011100100100 #
1$
b00110110000000101111100010101100 %
0&
0*
b00000000000000000000000000000000 +
#283
0$
b00000000000000000000000000000000 %
1&
1*
b10000100011001110011011100100100 +
#284
b01101110001010101000000100000100 #
1$
b11101001110000110100100111100000 %
0&
0*
b00000000000000000000000000000000 +
#285
0$
b00000000000000000000000000000000 %
1&
1*
b01101110001010101000000100000100 +
#286
b01011111100011010000100011101000 #
1$
b11110001011000101000011111100100 %
0&
0*
b00000000000000000000000000000000 +
#287
0$
b00000000000000000000000000000000 %
1&
1*
b01011111100011010000100011101000 +
